{
    "message_id": "35810a7b-0613-40d9-a048-f410a8bbc8f7",
    "timestamp": "2026-06-23T15:46:26.691157Z",
    "source_agent": "settlement_processor",
    "target_agent": "results",
    "data": {
        "transaction_id": "TXN008",
        "timestamp": "2026-03-16T10:15:00Z",
        "source_account": "ACC-****",
        "destination_account": "ACC-****",
        "amount": "3200.00",
        "currency": "USD",
        "transaction_type": "transfer",
        "description": "Salary advance",
        "metadata": {
            "channel": "mobile",
            "country": "US"
        },
        "status": "settled",
        "risk_score": 0.0,
        "risk_rules": [],
        "fraud_analysis": "I ran all four rules: high-value check (3200 < 10k ✓ pass), structuring check (not in 9k-10k range ✓ pass), off-hours check (10:15 UTC is normal hours ✓ pass), cross-border check (US to US ✓ pass). No triggers. Verdict: clean.",
        "settled_at": "2026-06-23T15:46:26.690843Z"
    }
}